spestly/__init__.py
spestly/odysseyxl.py
spestly-0.1.0.dist-info/LICENSE
spestly-0.1.0.dist-info/METADATA
spestly-0.1.0.dist-info/WHEEL
spestly-0.1.0.dist-info/top_level.txt
spestly-0.1.0.dist-info/RECORD
