Metadata-Version: 2.1
Name: spestly
Version: 0.1.0
Summary: A Python package for generating images using the OdysseyXL models.
Home-page: https://github.com/Aayan-Mishra/OdysseyXL
Author: Aayan Mishra
Author-email: aayan.mishra@proton.me
Classifier: Programming Language :: Python :: 3
Classifier: License :: OSI Approved :: MIT License
Classifier: Operating System :: OS Independent
Requires-Python: >=3.7
License-File: LICENSE
Requires-Dist: gradio-client
Requires-Dist: Pillow
Requires-Dist: requests
